robot_out_stream/__init__.py
robot_out_stream/_decoder.py
robot_out_stream/_impl.py
robot_out_stream/index.py
robot_out_stream/py.typed
robot_out_stream/robot_version.py
robot_out_stream/xml_to_rfstream.py
robotframework_output_stream-0.0.6.dist-info/METADATA
robotframework_output_stream-0.0.6.dist-info/WHEEL
robotframework_output_stream-0.0.6.dist-info/top_level.txt
robotframework_output_stream-0.0.6.dist-info/RECORD
