Metadata-Version: 2.1
Name: robotframework-output-stream
Version: 0.0.6
Summary: Robot Framework Output Stream (a RF listener to provide an output that's compact and streamable).
Home-page: https://github.com/robocorp/robotframework-output-stream
Author: Fabio Zadrozny
License: Apache-2.0
Classifier: Development Status :: 2 - Pre-Alpha
Classifier: Environment :: Console
Classifier: Intended Audience :: Developers
Classifier: License :: OSI Approved :: Apache Software License
Classifier: Operating System :: MacOS :: MacOS X
Classifier: Operating System :: Microsoft :: Windows
Classifier: Operating System :: POSIX
Classifier: Programming Language :: Python
Classifier: Programming Language :: Python :: 3.7
Classifier: Programming Language :: Python :: 3.8
Classifier: Programming Language :: Python :: 3.9
Classifier: Programming Language :: Python :: 3.10
Classifier: Programming Language :: Python :: 3.11
Classifier: Framework :: Robot Framework
Classifier: Framework :: Robot Framework :: Tool
Requires-Python: >=3.7
Requires-Dist: robotframework (>=3.2)
Provides-Extra: test
Requires-Dist: mock ; extra == 'test'
Requires-Dist: pytest ; extra == 'test'
Requires-Dist: pytest-regressions (==1.0.6) ; extra == 'test'
Requires-Dist: pytest-xdist ; extra == 'test'
Requires-Dist: pytest-timeout ; extra == 'test'
